dtpylog/__init__.py
dtpylog/api_handler.py
dtpylog/config.py
dtpylog/footprint.py
dtpylog/formatter.py
dtpylog/handlers.py
dtpylog/initializer.py
dtpylog-1.0.0.dist-info/METADATA
dtpylog-1.0.0.dist-info/WHEEL
dtpylog-1.0.0.dist-info/RECORD
