Metadata-Version: 2.3
Name: dtpylog
Version: 1.0.0
Summary: A light python package for advanced python log system.
License: MIT
Author: Reza Shirazi
Author-email: reza@datgate.com
Requires-Python: >=3.11.9,<3.12.0
Classifier: License :: OSI Approved :: MIT License
Classifier: Programming Language :: Python :: 3
Requires-Dist: requests (>=2.32.3,<2.33.0)
